mermaid_ascii/__init__.py
mermaid_ascii/mermaid-ascii
mermaid_ascii-0.6.1.post2.dist-info/LICENSE
mermaid_ascii-0.6.1.post2.dist-info/METADATA
mermaid_ascii-0.6.1.post2.dist-info/WHEEL
mermaid_ascii-0.6.1.post2.dist-info/entry_points.txt
mermaid_ascii-0.6.1.post2.dist-info/RECORD
